{"cameraMode":{"drawMode":0,"name":"Shaded","section":"Shading Mode"},"sceneLighting":true,"audioPlay":false,"sceneViewState":{"showFog":true,"showMaterialUpdate":false,"showSkybox":true,"showFlares":true,"showImageEffects":true,"showParticleSystems":true},"in2DMode":false,"pivot":{"x":1.3653645515441895,"y":10.748260498046875,"z":8.85664176940918},"rotation":{"x":-0.12728014588356019,"y":-0.05294237285852432,"z":0.006803551223129034,"w":-0.990430474281311},"size":8.02932357788086,"orthographic":false}